LICENSE
MANIFEST.in
README.rst
buildout.cfg
develop.cfg
requirements.txt
setup.py
version.txt
bob/__init__.py
bob.ip.flandmark.egg-info/PKG-INFO
bob.ip.flandmark.egg-info/SOURCES.txt
bob.ip.flandmark.egg-info/dependency_links.txt
bob.ip.flandmark.egg-info/not-zip-safe
bob.ip.flandmark.egg-info/requires.txt
bob.ip.flandmark.egg-info/top_level.txt
bob/ip/__init__.py
bob/ip/flandmark/__init__.py
bob/ip/flandmark/flandmark.cpp
bob/ip/flandmark/main.cpp
bob/ip/flandmark/test.py
bob/ip/flandmark/version.cpp
bob/ip/flandmark/cpp/flandmark_detector.cpp
bob/ip/flandmark/cpp/flandmark_detector.h
bob/ip/flandmark/cpp/liblbp.cpp
bob/ip/flandmark/cpp/liblbp.h
bob/ip/flandmark/data/flandmark_model.dat
bob/ip/flandmark/data/lena.jpg
bob/ip/flandmark/data/multi.jpg
doc/conf.py
doc/guide.rst
doc/index.rst
doc/links.rst
doc/py_api.rst
doc/plot/show_lena.py