Metadata-Version: 1.1
Name: bob.ip.flandmark
Version: 2.1.7
Summary: Flandmark keypoint localization library
Home-page: https://gitlab.idiap.ch/bob/bob.ip.flandmark
Author: Andre Anjos
Author-email: andre.anjos@idiap.ch
License: BSD
Platform: UNKNOWN
Classifier: Framework :: Bob
Classifier: Development Status :: 4 - Beta
Classifier: Intended Audience :: Developers
Classifier: License :: OSI Approved :: GNU General Public License v3 (GPLv3)
Classifier: Natural Language :: English
Classifier: Programming Language :: Python
Classifier: Topic :: Scientific/Engineering :: Artificial Intelligence
